[
  {
    "id": 1,
    "name": "NEW AVANZA",
    "description": "Mobil keluarga yang nyaman dan ideal untuk perjalanan bersama rombongan kecil.",
    "price": "350.000",
    "imageUrl": "/car/NA.png",
    "link": "https://wa.me/6281529408733?text=Halo%20Admin,%20saya%20tertarik%20untuk%20sewa%20mobil%20Toyota%20Avanza"
  },
  {
    "id": 2,
    "name": "INNOVA REBORN",
    "description": "Pilihan ekonomis dengan ruang yang cukup luas untuk perjalanan harian.",
    "price": "300.000",
    "imageUrl": "/car/IR.png",
    "link": "https://wa.me/6281529408733?text=Halo%20Admin,%20saya%20tertarik%20untuk%20sewa%20mobil%20Daihatsu%20Xenia"
  },
  {
    "id": 3,
    "name": "ELF",
    "description": "Mobil city car yang lincah, sempurna untuk berkeliling kota dengan mudah.",
    "price": "250.000",
    "imageUrl": "/car/E.png",
    "link": "https://wa.me/6281529408733?text=Halo%20Admin,%20saya%20tertarik%20untuk%20sewa%20mobil%20Honda%20Brio"
  },
  {
    "id": 4,
    "name": "HIACE",
    "description": "Mobil city car yang lincah, sempurna untuk berkeliling kota dengan mudah.",
    "price": "250.000",
    "imageUrl": "/car/HIA.png",
    "link": "https://wa.me/6281529408733?text=Halo%20Admin,%20saya%20tertarik%20untuk%20sewa%20mobil%20Honda%20Brio"
  },
  {
    "id": 5,
    "name": "FORTUNER",
    "description": "Mobil city car yang lincah, sempurna untuk berkeliling kota dengan mudah.",
    "price": "250.000",
    "imageUrl": "/car/FORT.png",
    "link": "https://wa.me/6281529408733?text=Halo%20Admin,%20saya%20tertarik%20untuk%20sewa%20mobil%20Honda%20Brio"
  },
  {
    "id": 6,
    "name": "PAJERO",
    "description": "Mobil city car yang lincah, sempurna untuk berkeliling kota dengan mudah.",
    "price": "250.000",
    "imageUrl": "/car/PAJERO.png",
    "link": "https://wa.me/6281529408733?text=Halo%20Admin,%20saya%20tertarik%20untuk%20sewa%20mobil%20Honda%20Brio"
  },
  {
    "id": 7,
    "name": "ZENIX",
    "description": "Mobil city car yang lincah, sempurna untuk berkeliling kota dengan mudah.",
    "price": "250.000",
    "imageUrl": "/car/ZEN.png",
    "link": "https://wa.me/6281529408733?text=Halo%20Admin,%20saya%20tertarik%20untuk%20sewa%20mobil%20Honda%20Brio"
  },
  {
    "id": 8,
    "name": "ALPHARD",
    "description": "Mobil city car yang lincah, sempurna untuk berkeliling kota dengan mudah.",
    "price": "250.000",
    "imageUrl": "/car/ALPH.png",
    "link": "https://wa.me/6281529408733?text=Halo%20Admin,%20saya%20tertarik%20untuk%20sewa%20mobil%20Honda%20Brio"
  },
  {
    "id": 9,
    "name": "BIG BUS",
    "description": "Mobil city car yang lincah, sempurna untuk berkeliling kota dengan mudah.",
    "price": "250.000",
    "imageUrl": "/car/BGBUS.png",
    "link": "https://wa.me/6281529408733?text=Halo%20Admin,%20saya%20tertarik%20untuk%20sewa%20mobil%20Honda%20Brio"
  },
  {
    "id": 10,
    "name": "MEDIUM BUS",
    "description": "Mobil city car yang lincah, sempurna untuk berkeliling kota dengan mudah.",
    "price": "250.000",
    "imageUrl": "/car/MDBUS.png",
    "link": "https://wa.me/6281529408733?text=Halo%20Admin,%20saya%20tertarik%20untuk%20sewa%20mobil%20Honda%20Brio"
  }
]